autork/__init__.py
autork/datamodels.py
autork/engine.py
autork/nmap_handler.py
autork/utils.py
autork-0.5.0.dist-info/METADATA
autork-0.5.0.dist-info/WHEEL
autork-0.5.0.dist-info/licenses/LICENSE
autork-0.5.0.dist-info/RECORD
