Metadata-Version: 2.4
Name: autork
Version: 0.5.0
Summary: A Python library for orchestrating Nmap scans, offering flexible control over scan types, NSE scripts, target management, and providing structured output with export options.
Project-URL: Homepage, https://github.com/JakeWerner/autork
Project-URL: Repository, https://github.com/JakeWerner/autork
Project-URL: Bug Tracker, https://github.com/JakeWerner/autork/issues
Author: Jacob Werner
License: Copyright (c) 2025 Jacob Werner
License-File: LICENSE
Keywords: automation,cybersecurity,ipv6,network,network mapping,nmap,nse,pentest,port scanner,reconnaissance,scanner,security
Classifier: Development Status :: 4 - Beta
Classifier: Intended Audience :: Developers
Classifier: Intended Audience :: Information Technology
Classifier: Intended Audience :: System Administrators
Classifier: License :: OSI Approved :: MIT License
Classifier: Operating System :: OS Independent
Classifier: Programming Language :: Python :: 3
Classifier: Programming Language :: Python :: 3.8
Classifier: Programming Language :: Python :: 3.9
Classifier: Programming Language :: Python :: 3.10
Classifier: Programming Language :: Python :: 3.11
Classifier: Programming Language :: Python :: 3.12
Classifier: Topic :: Security
Classifier: Topic :: Software Development :: Libraries :: Python Modules
Classifier: Topic :: System :: Networking
Classifier: Topic :: System :: Networking :: Monitoring
Classifier: Topic :: Utilities
Requires-Python: >=3.8
Provides-Extra: dev
Requires-Dist: build>=0.10; extra == 'dev'
Requires-Dist: pytest-mock>=3.0; extra == 'dev'
Requires-Dist: pytest>=7.0; extra == 'dev'
Requires-Dist: twine>=4.0; extra == 'dev'
Provides-Extra: test
Requires-Dist: pytest-mock>=3.0; extra == 'test'
Requires-Dist: pytest>=7.0; extra == 'test'
